WeiruanAiEduJiaochengFix1/README.md
WeiruanAiEduJiaochengFix1/__init__.py
WeiruanAiEduJiaochengFix1/__main__.py
WeiruanAiEduJiaochengFix1/file.epub
WeiruanAiEduJiaochengFix1/index.html
WeiruanAiEduJiaochengFix1/css/__init__.py
WeiruanAiEduJiaochengFix1/css/annotations.css
WeiruanAiEduJiaochengFix1/css/main.css
WeiruanAiEduJiaochengFix1/css/normalize.css
WeiruanAiEduJiaochengFix1/css/popup.css
WeiruanAiEduJiaochengFix1/font/__init__.py
WeiruanAiEduJiaochengFix1/font/fontello.eot
WeiruanAiEduJiaochengFix1/font/fontello.svg
WeiruanAiEduJiaochengFix1/font/fontello.ttf
WeiruanAiEduJiaochengFix1/font/fontello.woff
WeiruanAiEduJiaochengFix1/img/__init__.py
WeiruanAiEduJiaochengFix1/img/annotator-glyph-sprite.png
WeiruanAiEduJiaochengFix1/img/annotator-icon-sprite.png
WeiruanAiEduJiaochengFix1/img/apple-touch-icon.png
WeiruanAiEduJiaochengFix1/img/cancelfullscreen.png
WeiruanAiEduJiaochengFix1/img/close.png
WeiruanAiEduJiaochengFix1/img/fullscreen.png
WeiruanAiEduJiaochengFix1/img/loader.gif
WeiruanAiEduJiaochengFix1/img/menu-icon.png
WeiruanAiEduJiaochengFix1/img/save.png
WeiruanAiEduJiaochengFix1/img/saved.png
WeiruanAiEduJiaochengFix1/img/settings-s.png
WeiruanAiEduJiaochengFix1/img/settings.png
WeiruanAiEduJiaochengFix1/img/star.png
WeiruanAiEduJiaochengFix1/js/__init__.py
WeiruanAiEduJiaochengFix1/js/epub.js
WeiruanAiEduJiaochengFix1/js/epub.min.js
WeiruanAiEduJiaochengFix1/js/epub.min.map
WeiruanAiEduJiaochengFix1/js/hooks.min.js
WeiruanAiEduJiaochengFix1/js/hooks.min.map
WeiruanAiEduJiaochengFix1/js/reader.js
WeiruanAiEduJiaochengFix1/js/reader.js.map
WeiruanAiEduJiaochengFix1/js/reader.min.js
WeiruanAiEduJiaochengFix1/js/reader.min.map
WeiruanAiEduJiaochengFix1/js/hooks/__init__.py
WeiruanAiEduJiaochengFix1/js/hooks/extensions/__init__.py
WeiruanAiEduJiaochengFix1/js/hooks/extensions/highlight.js
WeiruanAiEduJiaochengFix1/js/libs/__init__.py
WeiruanAiEduJiaochengFix1/js/libs/jquery.min.js
WeiruanAiEduJiaochengFix1/js/libs/localforage.min.js
weiruan_ai_edu_jiaocheng_fix1-2025.3.25.1.dist-info/METADATA
weiruan_ai_edu_jiaocheng_fix1-2025.3.25.1.dist-info/WHEEL
weiruan_ai_edu_jiaocheng_fix1-2025.3.25.1.dist-info/entry_points.txt
weiruan_ai_edu_jiaocheng_fix1-2025.3.25.1.dist-info/top_level.txt
weiruan_ai_edu_jiaocheng_fix1-2025.3.25.1.dist-info/RECORD
